README.rst
setup.py
pyglins/__init__.py
pyglins.egg-info/PKG-INFO
pyglins.egg-info/SOURCES.txt
pyglins.egg-info/dependency_links.txt
pyglins.egg-info/top_level.txt
test/__init__.py