Metadata-Version: 1.1
Name: pyglins
Version: 0.1.1.dev1
Summary: Minimal plugin system for Python apps
Home-page: https://github.com/paxet/pyglins
Author: Javier Caballero
Author-email: paxet83@gmail.com
License: MIT
Keywords: plugin manager
Platform: UNKNOWN
Classifier: Development Status :: 1 - Planning
Classifier: Intended Audience :: Developers
Classifier: License :: OSI Approved :: MIT License
Classifier: Programming Language :: Python :: 3.4
Classifier: Programming Language :: Python :: 3.5
Classifier: Topic :: Software Development :: Libraries :: Python Modules
Classifier: Topic :: Utilities
Classifier: Operating System :: OS Independent
